terna/__init__.py
terna/terna.py
terna_py-0.5.5.dist-info/licenses/LICENSE
terna_py-0.5.5.dist-info/METADATA
terna_py-0.5.5.dist-info/WHEEL
terna_py-0.5.5.dist-info/top_level.txt
terna_py-0.5.5.dist-info/RECORD
